qa_ai/__init__.py
qa_ai/adapters/__init__.py
qa_ai/adapters/localai_adapter.py
qa_ai/adapters/mistral_adapter.py
qa_ai/adapters/openai_adapter.py
qa_ai/core/__init__.py
qa_ai/core/generator.py
qa_ai/models.py
qa_ai/prompts/__init__.py
qa_ai/prompts/web/__init__.py
qa_ai/prompts/web/login.md
qa_ai/prompts/web/test.md
qa_ai/prompts/web_tests.md
qa_ai/test_generator.py
qa_ai-0.2.5.dist-info/LICENCE
qa_ai-0.2.5.dist-info/METADATA
qa_ai-0.2.5.dist-info/WHEEL
qa_ai-0.2.5.dist-info/RECORD
